lona_redis/__init__.py
lona_redis/middlewares.py
lona_redis-0.0.dist-info/LICENSE.txt
lona_redis-0.0.dist-info/METADATA
lona_redis-0.0.dist-info/WHEEL
lona_redis-0.0.dist-info/top_level.txt
lona_redis-0.0.dist-info/RECORD
