Metadata-Version: 2.1
Name: lona-redis
Version: 0.0
Author-email: Florian Scherf <mail@florianscherf.de>
License: MIT License
Project-URL: Homepage, https://github.com/lona-web-org/lona-redis
Project-URL: Repository, https://github.com/lona-web-org/lona-redis
Project-URL: Bug Tracker, https://github.com/lona-web-org/lona-redis/issues
Classifier: License :: OSI Approved :: MIT License
Classifier: Programming Language :: Python :: 3 :: Only
Requires-Python: >=3.7
License-File: LICENSE.txt
Requires-Dist: lona
Provides-Extra: packaging
Requires-Dist: build ; extra == 'packaging'
Requires-Dist: twine ; extra == 'packaging'
Provides-Extra: testing
Requires-Dist: tox ; extra == 'testing'
Requires-Dist: coverage (==7.1.0) ; extra == 'testing'
Requires-Dist: pytest (==7.2.1) ; extra == 'testing'
